pyfritzhome/__init__.py
pyfritzhome/cli.py
pyfritzhome/errors.py
pyfritzhome/fritzhome.py
pyfritzhome/fritzhomedevice.py
pyfritzhome/devicetypes/__init__.py
pyfritzhome/devicetypes/fritzhomedevicealarm.py
pyfritzhome/devicetypes/fritzhomedevicebase.py
pyfritzhome/devicetypes/fritzhomedeviceblind.py
pyfritzhome/devicetypes/fritzhomedevicebutton.py
pyfritzhome/devicetypes/fritzhomedevicefeatures.py
pyfritzhome/devicetypes/fritzhomedevicehumidity.py
pyfritzhome/devicetypes/fritzhomedevicelevel.py
pyfritzhome/devicetypes/fritzhomedevicelightbulb.py
pyfritzhome/devicetypes/fritzhomedevicepowermeter.py
pyfritzhome/devicetypes/fritzhomedevicerepeater.py
pyfritzhome/devicetypes/fritzhomedeviceswitch.py
pyfritzhome/devicetypes/fritzhomedevicetemperature.py
pyfritzhome/devicetypes/fritzhomedevicethermostat.py
pyfritzhome/devicetypes/fritzhomeentitybase.py
pyfritzhome/devicetypes/fritzhometemplate.py
pyfritzhome/devicetypes/fritzhometrigger.py
pyfritzhome-0.6.19.dist-info/licenses/LICENSE
pyfritzhome-0.6.19.dist-info/METADATA
pyfritzhome-0.6.19.dist-info/WHEEL
pyfritzhome-0.6.19.dist-info/entry_points.txt
pyfritzhome-0.6.19.dist-info/top_level.txt
pyfritzhome-0.6.19.dist-info/RECORD
