Metadata-Version: 2.4
Name: pyfritzhome
Version: 0.6.19
Summary: Fritz!Box Smarthome Python Library
Home-page: http://github.com/hthiery/python-fritzhome
Author: Heiko Thiery
Author-email: heiko.thiery@gmail.com
License: MIT
Classifier: License :: OSI Approved :: MIT License
Classifier: Programming Language :: Python :: 3
Classifier: Programming Language :: Python :: 3.9
Classifier: Programming Language :: Python :: 3.10
Classifier: Programming Language :: Python :: 3.11
Classifier: Programming Language :: Python :: 3.12
Classifier: Programming Language :: Python :: 3.13
Classifier: Programming Language :: Python :: 3.14
Classifier: Programming Language :: Python :: Implementation :: CPython
Classifier: Programming Language :: Python :: Implementation :: PyPy
License-File: LICENSE
Requires-Dist: requests
Requires-Dist: cryptography
Dynamic: license-file
